antlr3runtime/Python/antlr3/__init__.py
antlr3runtime/Python/antlr3/compat.py
antlr3runtime/Python/antlr3/constants.py
antlr3runtime/Python/antlr3/debug.py
antlr3runtime/Python/antlr3/dfa.py
antlr3runtime/Python/antlr3/dottreegen.py
antlr3runtime/Python/antlr3/exceptions.py
antlr3runtime/Python/antlr3/extras.py
antlr3runtime/Python/antlr3/main.py
antlr3runtime/Python/antlr3/recognizers.py
antlr3runtime/Python/antlr3/streams.py
antlr3runtime/Python/antlr3/tokens.py
antlr3runtime/Python/antlr3/tree.py
antlr3runtime/Python/antlr3/treewizard.py
antlr3runtime/Python3/antlr3/__init__.py
antlr3runtime/Python3/antlr3/constants.py
antlr3runtime/Python3/antlr3/debug.py
antlr3runtime/Python3/antlr3/dfa.py
antlr3runtime/Python3/antlr3/exceptions.py
antlr3runtime/Python3/antlr3/main.py
antlr3runtime/Python3/antlr3/recognizers.py
antlr3runtime/Python3/antlr3/streams.py
antlr3runtime/Python3/antlr3/tokens.py
antlr3runtime/Python3/antlr3/tree.py
antlr3runtime/Python3/antlr3/treewizard.py
congress/__init__.py
congress/auth.py
congress/context.py
congress/data_types.py
congress/encryption.py
congress/exception.py
congress/harness.py
congress/opts.py
congress/service.py
congress/utils.py
congress/version.py
congress/api/__init__.py
congress/api/action_model.py
congress/api/api_utils.py
congress/api/application.py
congress/api/base.py
congress/api/datasource_model.py
congress/api/error_codes.py
congress/api/library_policy_model.py
congress/api/policy_model.py
congress/api/router.py
congress/api/row_model.py
congress/api/rule_model.py
congress/api/schema_model.py
congress/api/status_model.py
congress/api/table_model.py
congress/api/versions.py
congress/api/webhook_model.py
congress/api/webservice.py
congress/api/system/__init__.py
congress/api/system/driver_model.py
congress/cfg_validator/__init__.py
congress/cfg_validator/parsing.py
congress/cfg_validator/utils.py
congress/cfg_validator/agent/__init__.py
congress/cfg_validator/agent/agent.py
congress/cfg_validator/agent/generator.py
openstack_congress-11.0.0.dist-info/AUTHORS
openstack_congress-11.0.0.dist-info/LICENSE
openstack_congress-11.0.0.dist-info/METADATA
openstack_congress-11.0.0.dist-info/WHEEL
openstack_congress-11.0.0.dist-info/entry_points.txt
openstack_congress-11.0.0.dist-info/pbr.json
openstack_congress-11.0.0.dist-info/top_level.txt
openstack_congress-11.0.0.dist-info/RECORD
