Metadata-Version: 2.1
Name: openstack-congress
Version: 11.0.0
Summary: Congress: The open policy framework for the cloud.
Home-page: https://docs.openstack.org/congress/latest/
Author: OpenStack
Author-email: openstack-discuss@lists.openstack.org
License: UNKNOWN
Platform: UNKNOWN
Classifier: Environment :: OpenStack
Classifier: Intended Audience :: Information Technology
Classifier: Intended Audience :: System Administrators
Classifier: License :: OSI Approved :: Apache Software License
Classifier: Operating System :: POSIX :: Linux
Classifier: Programming Language :: Python
Classifier: Programming Language :: Python :: 3
Classifier: Programming Language :: Python :: 3.6
Classifier: Programming Language :: Python :: 3.7
Requires-Dist: eventlet (!=0.18.3,!=0.20.1,!=0.23.0,!=0.25.0,>=0.18.2)
Requires-Dist: jsonschema (>=2.6.0)
Requires-Dist: PuLP (>=1.4.1)
Requires-Dist: keystoneauth1 (>=3.4.0)
Requires-Dist: keystonemiddleware (>=4.17.0)
Requires-Dist: Paste (>=2.0.2)
Requires-Dist: PasteDeploy (>=1.5.0)
Requires-Dist: pbr (!=2.1.0,>=2.0.0)
Requires-Dist: aodhclient (>=0.9.0)
Requires-Dist: python-tackerclient (>=0.8.0)
Requires-Dist: python-keystoneclient (>=3.8.0)
Requires-Dist: python-heatclient (>=1.10.0)
Requires-Dist: python-monascaclient (>=1.12.1)
Requires-Dist: python-muranoclient (>=0.8.2)
Requires-Dist: python-novaclient (>=9.1.0)
Requires-Dist: python-neutronclient (>=6.7.0)
Requires-Dist: python-cinderclient (>=3.3.0)
Requires-Dist: python-swiftclient (>=3.2.0)
Requires-Dist: python-ironicclient (>=2.3.0)
Requires-Dist: python-mistralclient (!=3.2.0,>=3.1.0)
Requires-Dist: alembic (>=0.8.10)
Requires-Dist: cryptography (>=2.1)
Requires-Dist: netaddr (>=0.7.18)
Requires-Dist: jsonpath-rw (<2.0,>=1.2.0)
Requires-Dist: psycopg2 (>=2.5.1)
Requires-Dist: python-dateutil (>=2.5.3)
Requires-Dist: python-glanceclient (>=2.8.0)
Requires-Dist: requests (!=2.20.0,>=2.14.2)
Requires-Dist: Routes (>=2.3.1)
Requires-Dist: six (>=1.10.0)
Requires-Dist: tenacity (>=4.4.0)
Requires-Dist: oslo.concurrency (>=3.26.0)
Requires-Dist: oslo.config (>=5.2.0)
Requires-Dist: oslo.context (>=2.19.2)
Requires-Dist: oslo.db (>=4.27.0)
Requires-Dist: oslo.messaging (>=5.29.0)
Requires-Dist: oslo.policy (>=1.30.0)
Requires-Dist: oslo.serialization (!=2.19.1,>=2.18.0)
Requires-Dist: oslo.service (!=1.28.1,>=1.24.0)
Requires-Dist: oslo.upgradecheck (>=0.1.0)
Requires-Dist: oslo.utils (>=3.33.0)
Requires-Dist: oslo.middleware (>=3.31.0)
Requires-Dist: oslo.vmware (>=2.17.0)
Requires-Dist: oslo.log (>=3.36.0)
Requires-Dist: WebOb (>=1.7.1)
Requires-Dist: PyYAML (>=3.10.0)
